yampit/__init__.py
yampit/mapper.py
yampit/polytope_request_handler.py
yampit/py.typed
yampit-0.3.0.dist-info/METADATA
yampit-0.3.0.dist-info/WHEEL
yampit-0.3.0.dist-info/RECORD
